chatdbt/__init__.py
chatdbt/chat.py
chatdbt/dbt_doc_resolver/__init__.py
chatdbt/dbt_doc_resolver/localfs.py
chatdbt/i18n.py
chatdbt/model.py
chatdbt/openai.py
chatdbt/shortcut.py
chatdbt/tiktoken_provider/__init__.py
chatdbt/tiktoken_provider/tiktoken_http_server.py
chatdbt/vector_storage/__init__.py
chatdbt/vector_storage/atlas.py
chatdbt/vector_storage/pgvector.py
chatdbt-0.0.5.dist-info/METADATA
chatdbt-0.0.5.dist-info/WHEEL
chatdbt-0.0.5.dist-info/RECORD
