Metadata-Version: 2.1
Name: chatdbt
Version: 0.0.5
Summary: chatdbt is an openai-based dbt documentation robot. You can use natural language to describe your data query requirements to the robot, and chatdbt will help you select the dbt model you need, or generate sql responses based on these dbt models to meet your need
Author: cadl
Author-email: ctrlaltdeleteliu@gmail.com
Requires-Python: >=3.7.1,<3.11
Classifier: Programming Language :: Python :: 3
Classifier: Programming Language :: Python :: 3.8
Classifier: Programming Language :: Python :: 3.9
Classifier: Programming Language :: Python :: 3.10
Provides-Extra: nomic
Provides-Extra: pgvector
Requires-Dist: nomic (>=1.0,<2.0) ; extra == "nomic"
Requires-Dist: openai[datalib,embeddings] (>=0.27,<0.28)
Requires-Dist: pgvector (>=0.1,<0.2) ; extra == "pgvector"
Requires-Dist: psycopg[binary] (>=3,<4) ; extra == "pgvector"
Requires-Dist: pydantic (>=1.9,<2.0)
Requires-Dist: requests (>=2.28,<3.0)
Requires-Dist: sqlalchemy (>=2,<3) ; extra == "pgvector"
Requires-Dist: tenacity (>=8,<9)
